LICENSE
MANIFEST.in
README.rst
setup.py
bin/slurm-limiter
slurm_toys/__init__.py
slurm_toys.egg-info/PKG-INFO
slurm_toys.egg-info/SOURCES.txt
slurm_toys.egg-info/dependency_links.txt
slurm_toys.egg-info/requires.txt
slurm_toys.egg-info/top_level.txt