Metadata-Version: 1.1
Name: slurm-toys
Version: 1.0.1
Summary: helper tools for the SLURM HPC workload manager used at Fred Hutch and elsewhere
Home-page: https://github.com/FredHutch/slurm-toys
Author: Dirk Petersen
Author-email: dp@nowhere.com
License: UNKNOWN
Download-URL: https://github.com/FredHutch/slurm-toys/tarball/1.0.1
Keywords: slurm,hpc,scientific computing
Platform: UNKNOWN
Classifier: Development Status :: 5 - Production/Stable
Classifier: Environment :: Console
Classifier: Intended Audience :: Developers
Classifier: Intended Audience :: Science/Research
Classifier: Intended Audience :: System Administrators
Classifier: License :: OSI Approved :: Apache Software License
Classifier: Natural Language :: English
Classifier: Operating System :: POSIX :: Linux
Classifier: Programming Language :: Python :: 3
Classifier: Programming Language :: Python :: 3.5
Classifier: Programming Language :: Python :: 3.6
Classifier: Programming Language :: Python :: Implementation :: CPython
Classifier: Programming Language :: Unix Shell
Classifier: Topic :: Software Development :: Libraries :: Python Modules
Classifier: Topic :: System :: Systems Administration
Classifier: Topic :: Utilities
